predictnow/__init__.py
predictnow/find_files_with_specific_extensions.py
predictnow/notifier.py
predictnow/pdapi.py
predictnow/predict_result.py
predictnow/training_result.py
pnow_client-0.1.2.dist-info/LICENSE
pnow_client-0.1.2.dist-info/METADATA
pnow_client-0.1.2.dist-info/WHEEL
pnow_client-0.1.2.dist-info/top_level.txt
pnow_client-0.1.2.dist-info/RECORD
