Metadata-Version: 2.1
Name: pnow-client
Version: 0.1.2
Summary: A restful client library, designed to access predictnow restful api.
Author: PredictNow.AI
Author-email: tech@predictnow.ai
Classifier: Programming Language :: Python :: 3
Classifier: Operating System :: OS Independent
Requires-Python: >=3.7
License-File: LICENSE
Requires-Dist: pandas (>=1.1.3)
Requires-Dist: firebase-admin (>=4.4.0)
Requires-Dist: requests (>=2.27.1)
Requires-Dist: pyarrow (>=10.0.0)
